aria/__init__.py
aria/ops/__init__.py
aria/ops/adapter_instance.py
aria/ops/adapter_logging.py
aria/ops/certificate_info.py
aria/ops/data.py
aria/ops/event.py
aria/ops/object.py
aria/ops/pipe_utils.py
aria/ops/py.typed
aria/ops/result.py
aria/ops/suite_api_client.py
aria/ops/timer.py
aria/ops/definition/__init__.py
aria/ops/definition/adapter_definition.py
aria/ops/definition/assertions.py
aria/ops/definition/attribute.py
aria/ops/definition/credential_type.py
aria/ops/definition/exceptions.py
aria/ops/definition/group.py
aria/ops/definition/object_type.py
aria/ops/definition/parameter.py
aria/ops/definition/py.typed
aria/ops/definition/units.py
vmware_aria_operations_integration_sdk_lib-1.1.0.dist-info/LICENSE
vmware_aria_operations_integration_sdk_lib-1.1.0.dist-info/METADATA
vmware_aria_operations_integration_sdk_lib-1.1.0.dist-info/NOTICE
vmware_aria_operations_integration_sdk_lib-1.1.0.dist-info/WHEEL
vmware_aria_operations_integration_sdk_lib-1.1.0.dist-info/top_level.txt
vmware_aria_operations_integration_sdk_lib-1.1.0.dist-info/RECORD
