Metadata-Version: 2.2
Name: vmware-aria-operations-integration-sdk-lib
Version: 1.1.0
Summary: Object model for interacting with the VMware Cloud Foundation Operations Containerized API
Home-page: https://github.com/vmware/vmware-aria-operations-integration-sdk
Author: Broadcom
Author-email: kyle.rokos@broadcom.com
Project-URL: Bug Tracker, https://github.com/vmware/vmware-aria-operations-integration-sdk/issues
Classifier: Programming Language :: Python :: 3
Classifier: License :: OSI Approved :: Apache Software License
Classifier: Intended Audience :: Information Technology
Classifier: Intended Audience :: System Administrators
Classifier: Intended Audience :: Developers
Classifier: Operating System :: OS Independent
Requires-Python: >=3.6
License-File: LICENSE
License-File: NOTICE
Requires-Dist: aenum==3.1.11
Requires-Dist: cryptography==44.0.0
